openbb_devtools/__init__.py
openbb_devtools-1.5.4.dist-info/METADATA
openbb_devtools-1.5.4.dist-info/WHEEL
openbb_devtools-1.5.4.dist-info/RECORD
